sentry_export
