Metadata-Version: 1.0
Name: sentry-export
Version: 0.9.0
Summary: A Sentry extension for exporting event data
Home-page: http://github.com/dmclain/sentry-export
Author: Dave McLain
Author-email: dmclain@gmail.com
License: MIT
Platform: UNKNOWN
Classifier: Intended Audience :: Developers
Classifier: Intended Audience :: System Administrators
Classifier: Operating System :: OS Independent
Classifier: License :: OSI Approved :: MIT License
Classifier: Programming Language :: Python
Classifier: Topic :: Software Development
